mlbi_dataset/__init__.py
mlbi_dataset/load_data.py
mlbi_datasets/__init__.py
mlbi_datasets/load_data.py
mlbi_datasets-0.2.3.dist-info/licenses/LICENSE
scodaviz/__init__.py
scodaviz/load_data.py
scodaviz/pl.py
scodaviz/supp.py
mlbi_datasets-0.2.3.dist-info/METADATA
mlbi_datasets-0.2.3.dist-info/WHEEL
mlbi_datasets-0.2.3.dist-info/entry_points.txt
mlbi_datasets-0.2.3.dist-info/top_level.txt
mlbi_datasets-0.2.3.dist-info/RECORD
